compiam/__init__.py
compiam/data.py
compiam/exceptions.py
compiam/io.py
compiam/version.py
compiam/conf/raga/carnatic.yaml
compiam/conf/raga/svara_cents.yaml
compiam/dunya/__init__.py
compiam/melody/__init__.py
compiam/melody/pattern/__init__.py
compiam/melody/pattern/sancara_search/__init__.py
compiam/melody/pattern/sancara_search/complex_auto/__init__.py
compiam/melody/pattern/sancara_search/complex_auto/complex.py
compiam/melody/pattern/sancara_search/complex_auto/cqt.py
compiam/melody/pattern/sancara_search/complex_auto/util.py
compiam/melody/pattern/sancara_search/extraction/__init__.py
compiam/melody/pattern/sancara_search/extraction/evaluation.py
compiam/melody/pattern/sancara_search/extraction/img.py
compiam/melody/pattern/sancara_search/extraction/io.py
compiam/melody/pattern/sancara_search/extraction/pitch.py
compiam/melody/pattern/sancara_search/extraction/segments.py
compiam/melody/pattern/sancara_search/extraction/self_sim.py
compiam/melody/pattern/sancara_search/extraction/sequence.py
compiam/melody/pattern/sancara_search/extraction/utils.py
compiam/melody/pattern/sancara_search/extraction/visualisation.py
compiam/melody/pitch_extraction/__init__.py
compiam/melody/pitch_extraction/melodia.py
compiam/melody/pitch_extraction/ftanet_carnatic/__init__.py
compiam/melody/pitch_extraction/ftanet_carnatic/cfp.py
compiam/melody/pitch_extraction/ftanet_carnatic/pitch_processing.py
compiam/melody/pitch_extraction/ftaresnet_carnatic/__init__.py
compiam/melody/pitch_extraction/ftaresnet_carnatic/model.py
compiam/melody/raga_recognition/__init__.py
compiam/melody/raga_recognition/deepsrgm/__init__.py
compiam/melody/raga_recognition/deepsrgm/attention_layer.py
compiam/melody/raga_recognition/deepsrgm/model.py
compiam/melody/raga_recognition/deepsrgm/raga_mapping.py
compiam/melody/tonic_identification/__init__.py
compiam/melody/tonic_identification/tonic_multipitch.py
compiam/models/README.md
compiam/rhythm/__init__.py
compiam/rhythm/meter/__init__.py
compiam-0.4.1.dist-info/AUTHORS
compiam-0.4.1.dist-info/COPYING
compiam-0.4.1.dist-info/METADATA
compiam-0.4.1.dist-info/WHEEL
compiam-0.4.1.dist-info/top_level.txt
compiam-0.4.1.dist-info/RECORD
