Metadata-Version: 2.1
Name: compiam
Version: 0.4.1
Summary: Common tools for the computational analysis of Indian Art Music.
License:                     GNU AFFERO GENERAL PUBLIC LICENSE
Project-URL: Homepage, https://github.com/MTG/compIAM
Project-URL: Documentation, https://mtg.github.io/compIAM/
Project-URL: Issues, https://github.com/MTG/compIAM/issues/
Project-URL: Releases, https://github.com/MTG/compIAM/releases/
Keywords: carnatic,hindustani,models,datasets,tools
Classifier: License :: OSI Approved :: GNU General Public License v3 or later (GPLv3+)
Classifier: Programming Language :: Python
Classifier: Development Status :: 3 - Alpha
Classifier: Intended Audience :: Science/Research
Classifier: Topic :: Multimedia :: Sound/Audio :: Analysis
Classifier: Programming Language :: Python :: 3.9
Classifier: Programming Language :: Python :: 3.10
Classifier: Programming Language :: Python :: 3.11
Requires-Python: >=3.9
License-File: COPYING
License-File: AUTHORS
Requires-Dist: attrs>=23.1.0
Requires-Dist: matplotlib>=3.0.0
Requires-Dist: numpy<=1.26.4,>=1.20.3
Requires-Dist: joblib>=1.2.0
Requires-Dist: pathlib~=1.0.1
Requires-Dist: tqdm>=4.66.1
Requires-Dist: IPython>=7.34.0
Requires-Dist: ipywidgets<8,>=7.0.0
Requires-Dist: Jinja2~=3.1.2
Requires-Dist: configobj~=5.0.6
Requires-Dist: seaborn
Requires-Dist: librosa>=0.10.1
Requires-Dist: soundfile>=0.12.1
Requires-Dist: scikit-learn~=1.5.2
Requires-Dist: scikit-image~=0.24.0
Requires-Dist: opencv-python~=4.6.0
Requires-Dist: hmmlearn==0.3.3
Requires-Dist: fastdtw~=0.3.4
Requires-Dist: compmusic==0.4
Requires-Dist: mirdata==0.3.9
Provides-Extra: tests
Requires-Dist: decorator>=5.1.1; extra == "tests"
Requires-Dist: pytest>=7.2.0; extra == "tests"
Requires-Dist: future>=0.18.3; extra == "tests"
Requires-Dist: black>=23.3.0; extra == "tests"
Provides-Extra: docs
Requires-Dist: numpydoc; extra == "docs"
Requires-Dist: recommonmark; extra == "docs"
Requires-Dist: sphinx>=3.4.0; extra == "docs"
Requires-Dist: sphinxcontrib-napoleon; extra == "docs"
Requires-Dist: sphinx_rtd_theme; extra == "docs"
Requires-Dist: sphinx-togglebutton; extra == "docs"
Provides-Extra: tensorflow
Requires-Dist: keras<3.0.0; extra == "tensorflow"
Requires-Dist: tensorflow==2.15.0; extra == "tensorflow"
Provides-Extra: torch
Requires-Dist: torch==2.0.0; extra == "torch"
Requires-Dist: torchaudio==2.0.1; extra == "torch"
Provides-Extra: essentia
Requires-Dist: essentia; extra == "essentia"
